<?xml version="1.0" encoding="utf-8"?>
<PermissionSets>
  <PermissionSet RoleID="DG PROTEMAX CUSTOM" RoleName="DG Protemax Custom">
    <Permission>
      <ObjectID>80107</ObjectID>
      <ObjectType>0</ObjectType>
      <ReadPermission>1</ReadPermission>
      <InsertPermission>1</InsertPermission>
      <ModifyPermission>1</ModifyPermission>
      <DeletePermission>1</DeletePermission>
      <ExecutePermission>0</ExecutePermission>
      <SecurityFilter />
    </Permission>
    <Permission>
      <ObjectID>80107</ObjectID>
      <ObjectType>1</ObjectType>
      <ReadPermission>0</ReadPermission>
      <InsertPermission>0</InsertPermission>
      <ModifyPermission>0</ModifyPermission>
      <DeletePermission>0</DeletePermission>
      <ExecutePermission>1</ExecutePermission>
      <SecurityFilter />
    </Permission>
    <Permission>
      <ObjectID>80104</ObjectID>
      <ObjectType>0</ObjectType>
      <ReadPermission>1</ReadPermission>
      <InsertPermission>1</InsertPermission>
      <ModifyPermission>1</ModifyPermission>
      <DeletePermission>1</DeletePermission>
      <ExecutePermission>0</ExecutePermission>
      <SecurityFilter />
    </Permission>
    <Permission>
      <ObjectID>80104</ObjectID>
      <ObjectType>1</ObjectType>
      <ReadPermission>0</ReadPermission>
      <InsertPermission>0</InsertPermission>
      <ModifyPermission>0</ModifyPermission>
      <DeletePermission>0</DeletePermission>
      <ExecutePermission>1</ExecutePermission>
      <SecurityFilter />
    </Permission>
    <Permission>
      <ObjectID>80102</ObjectID>
      <ObjectType>0</ObjectType>
      <ReadPermission>1</ReadPermission>
      <InsertPermission>1</InsertPermission>
      <ModifyPermission>1</ModifyPermission>
      <DeletePermission>1</DeletePermission>
      <ExecutePermission>0</ExecutePermission>
      <SecurityFilter />
    </Permission>
    <Permission>
      <ObjectID>80102</ObjectID>
      <ObjectType>1</ObjectType>
      <ReadPermission>0</ReadPermission>
      <InsertPermission>0</InsertPermission>
      <ModifyPermission>0</ModifyPermission>
      <DeletePermission>0</DeletePermission>
      <ExecutePermission>1</ExecutePermission>
      <SecurityFilter />
    </Permission>
    <Permission>
      <ObjectID>80103</ObjectID>
      <ObjectType>0</ObjectType>
      <ReadPermission>1</ReadPermission>
      <InsertPermission>1</InsertPermission>
      <ModifyPermission>1</ModifyPermission>
      <DeletePermission>1</DeletePermission>
      <ExecutePermission>0</ExecutePermission>
      <SecurityFilter />
    </Permission>
    <Permission>
      <ObjectID>80103</ObjectID>
      <ObjectType>1</ObjectType>
      <ReadPermission>0</ReadPermission>
      <InsertPermission>0</InsertPermission>
      <ModifyPermission>0</ModifyPermission>
      <DeletePermission>0</DeletePermission>
      <ExecutePermission>1</ExecutePermission>
      <SecurityFilter />
    </Permission>
    <Permission>
      <ObjectID>80105</ObjectID>
      <ObjectType>0</ObjectType>
      <ReadPermission>1</ReadPermission>
      <InsertPermission>1</InsertPermission>
      <ModifyPermission>1</ModifyPermission>
      <DeletePermission>1</DeletePermission>
      <ExecutePermission>0</ExecutePermission>
      <SecurityFilter />
    </Permission>
    <Permission>
      <ObjectID>80105</ObjectID>
      <ObjectType>1</ObjectType>
      <ReadPermission>0</ReadPermission>
      <InsertPermission>0</InsertPermission>
      <ModifyPermission>0</ModifyPermission>
      <DeletePermission>0</DeletePermission>
      <ExecutePermission>1</ExecutePermission>
      <SecurityFilter />
    </Permission>
    <Permission>
      <ObjectID>80108</ObjectID>
      <ObjectType>0</ObjectType>
      <ReadPermission>1</ReadPermission>
      <InsertPermission>1</InsertPermission>
      <ModifyPermission>1</ModifyPermission>
      <DeletePermission>1</DeletePermission>
      <ExecutePermission>0</ExecutePermission>
      <SecurityFilter />
    </Permission>
    <Permission>
      <ObjectID>80108</ObjectID>
      <ObjectType>1</ObjectType>
      <ReadPermission>0</ReadPermission>
      <InsertPermission>0</InsertPermission>
      <ModifyPermission>0</ModifyPermission>
      <DeletePermission>0</DeletePermission>
      <ExecutePermission>1</ExecutePermission>
      <SecurityFilter />
    </Permission>
    <Permission>
      <ObjectID>80106</ObjectID>
      <ObjectType>0</ObjectType>
      <ReadPermission>1</ReadPermission>
      <InsertPermission>1</InsertPermission>
      <ModifyPermission>1</ModifyPermission>
      <DeletePermission>1</DeletePermission>
      <ExecutePermission>0</ExecutePermission>
      <SecurityFilter />
    </Permission>
    <Permission>
      <ObjectID>80106</ObjectID>
      <ObjectType>1</ObjectType>
      <ReadPermission>0</ReadPermission>
      <InsertPermission>0</InsertPermission>
      <ModifyPermission>0</ModifyPermission>
      <DeletePermission>0</DeletePermission>
      <ExecutePermission>1</ExecutePermission>
      <SecurityFilter />
    </Permission>
    <Permission>
      <ObjectID>80101</ObjectID>
      <ObjectType>0</ObjectType>
      <ReadPermission>1</ReadPermission>
      <InsertPermission>1</InsertPermission>
      <ModifyPermission>1</ModifyPermission>
      <DeletePermission>1</DeletePermission>
      <ExecutePermission>0</ExecutePermission>
      <SecurityFilter />
    </Permission>
    <Permission>
      <ObjectID>80101</ObjectID>
      <ObjectType>1</ObjectType>
      <ReadPermission>0</ReadPermission>
      <InsertPermission>0</InsertPermission>
      <ModifyPermission>0</ModifyPermission>
      <DeletePermission>0</DeletePermission>
      <ExecutePermission>1</ExecutePermission>
      <SecurityFilter />
    </Permission>
    <Permission>
      <ObjectID>80100</ObjectID>
      <ObjectType>0</ObjectType>
      <ReadPermission>1</ReadPermission>
      <InsertPermission>1</InsertPermission>
      <ModifyPermission>1</ModifyPermission>
      <DeletePermission>1</DeletePermission>
      <ExecutePermission>0</ExecutePermission>
      <SecurityFilter />
    </Permission>
    <Permission>
      <ObjectID>80100</ObjectID>
      <ObjectType>1</ObjectType>
      <ReadPermission>0</ReadPermission>
      <InsertPermission>0</InsertPermission>
      <ModifyPermission>0</ModifyPermission>
      <DeletePermission>0</DeletePermission>
      <ExecutePermission>1</ExecutePermission>
      <SecurityFilter />
    </Permission>
    <Permission>
      <ObjectID>80109</ObjectID>
      <ObjectType>0</ObjectType>
      <ReadPermission>1</ReadPermission>
      <InsertPermission>1</InsertPermission>
      <ModifyPermission>1</ModifyPermission>
      <DeletePermission>1</DeletePermission>
      <ExecutePermission>0</ExecutePermission>
      <SecurityFilter />
    </Permission>
    <Permission>
      <ObjectID>80109</ObjectID>
      <ObjectType>1</ObjectType>
      <ReadPermission>0</ReadPermission>
      <InsertPermission>0</InsertPermission>
      <ModifyPermission>0</ModifyPermission>
      <DeletePermission>0</DeletePermission>
      <ExecutePermission>1</ExecutePermission>
      <SecurityFilter />
    </Permission>
    <Permission>
      <ObjectID>80100</ObjectID>
      <ObjectType>5</ObjectType>
      <ReadPermission>0</ReadPermission>
      <InsertPermission>0</InsertPermission>
      <ModifyPermission>0</ModifyPermission>
      <DeletePermission>0</DeletePermission>
      <ExecutePermission>1</ExecutePermission>
      <SecurityFilter />
    </Permission>
    <Permission>
      <ObjectID>80114</ObjectID>
      <ObjectType>8</ObjectType>
      <ReadPermission>0</ReadPermission>
      <InsertPermission>0</InsertPermission>
      <ModifyPermission>0</ModifyPermission>
      <DeletePermission>0</DeletePermission>
      <ExecutePermission>1</ExecutePermission>
      <SecurityFilter />
    </Permission>
    <Permission>
      <ObjectID>80115</ObjectID>
      <ObjectType>8</ObjectType>
      <ReadPermission>0</ReadPermission>
      <InsertPermission>0</InsertPermission>
      <ModifyPermission>0</ModifyPermission>
      <DeletePermission>0</DeletePermission>
      <ExecutePermission>1</ExecutePermission>
      <SecurityFilter />
    </Permission>
    <Permission>
      <ObjectID>80105</ObjectID>
      <ObjectType>8</ObjectType>
      <ReadPermission>0</ReadPermission>
      <InsertPermission>0</InsertPermission>
      <ModifyPermission>0</ModifyPermission>
      <DeletePermission>0</DeletePermission>
      <ExecutePermission>1</ExecutePermission>
      <SecurityFilter />
    </Permission>
    <Permission>
      <ObjectID>80111</ObjectID>
      <ObjectType>8</ObjectType>
      <ReadPermission>0</ReadPermission>
      <InsertPermission>0</InsertPermission>
      <ModifyPermission>0</ModifyPermission>
      <DeletePermission>0</DeletePermission>
      <ExecutePermission>1</ExecutePermission>
      <SecurityFilter />
    </Permission>
    <Permission>
      <ObjectID>80112</ObjectID>
      <ObjectType>8</ObjectType>
      <ReadPermission>0</ReadPermission>
      <InsertPermission>0</InsertPermission>
      <ModifyPermission>0</ModifyPermission>
      <DeletePermission>0</DeletePermission>
      <ExecutePermission>1</ExecutePermission>
      <SecurityFilter />
    </Permission>
    <Permission>
      <ObjectID>80104</ObjectID>
      <ObjectType>8</ObjectType>
      <ReadPermission>0</ReadPermission>
      <InsertPermission>0</InsertPermission>
      <ModifyPermission>0</ModifyPermission>
      <DeletePermission>0</DeletePermission>
      <ExecutePermission>1</ExecutePermission>
      <SecurityFilter />
    </Permission>
    <Permission>
      <ObjectID>80113</ObjectID>
      <ObjectType>8</ObjectType>
      <ReadPermission>0</ReadPermission>
      <InsertPermission>0</InsertPermission>
      <ModifyPermission>0</ModifyPermission>
      <DeletePermission>0</DeletePermission>
      <ExecutePermission>1</ExecutePermission>
      <SecurityFilter />
    </Permission>
    <Permission>
      <ObjectID>80106</ObjectID>
      <ObjectType>8</ObjectType>
      <ReadPermission>0</ReadPermission>
      <InsertPermission>0</InsertPermission>
      <ModifyPermission>0</ModifyPermission>
      <DeletePermission>0</DeletePermission>
      <ExecutePermission>1</ExecutePermission>
      <SecurityFilter />
    </Permission>
    <Permission>
      <ObjectID>80102</ObjectID>
      <ObjectType>8</ObjectType>
      <ReadPermission>0</ReadPermission>
      <InsertPermission>0</InsertPermission>
      <ModifyPermission>0</ModifyPermission>
      <DeletePermission>0</DeletePermission>
      <ExecutePermission>1</ExecutePermission>
      <SecurityFilter />
    </Permission>
    <Permission>
      <ObjectID>80107</ObjectID>
      <ObjectType>8</ObjectType>
      <ReadPermission>0</ReadPermission>
      <InsertPermission>0</InsertPermission>
      <ModifyPermission>0</ModifyPermission>
      <DeletePermission>0</DeletePermission>
      <ExecutePermission>1</ExecutePermission>
      <SecurityFilter />
    </Permission>
    <Permission>
      <ObjectID>80101</ObjectID>
      <ObjectType>8</ObjectType>
      <ReadPermission>0</ReadPermission>
      <InsertPermission>0</InsertPermission>
      <ModifyPermission>0</ModifyPermission>
      <DeletePermission>0</DeletePermission>
      <ExecutePermission>1</ExecutePermission>
      <SecurityFilter />
    </Permission>
    <Permission>
      <ObjectID>80103</ObjectID>
      <ObjectType>8</ObjectType>
      <ReadPermission>0</ReadPermission>
      <InsertPermission>0</InsertPermission>
      <ModifyPermission>0</ModifyPermission>
      <DeletePermission>0</DeletePermission>
      <ExecutePermission>1</ExecutePermission>
      <SecurityFilter />
    </Permission>
    <Permission>
      <ObjectID>80100</ObjectID>
      <ObjectType>8</ObjectType>
      <ReadPermission>0</ReadPermission>
      <InsertPermission>0</InsertPermission>
      <ModifyPermission>0</ModifyPermission>
      <DeletePermission>0</DeletePermission>
      <ExecutePermission>1</ExecutePermission>
      <SecurityFilter />
    </Permission>
    <Permission>
      <ObjectID>80116</ObjectID>
      <ObjectType>8</ObjectType>
      <ReadPermission>0</ReadPermission>
      <InsertPermission>0</InsertPermission>
      <ModifyPermission>0</ModifyPermission>
      <DeletePermission>0</DeletePermission>
      <ExecutePermission>1</ExecutePermission>
      <SecurityFilter />
    </Permission>
    <Permission>
      <ObjectID>80108</ObjectID>
      <ObjectType>8</ObjectType>
      <ReadPermission>0</ReadPermission>
      <InsertPermission>0</InsertPermission>
      <ModifyPermission>0</ModifyPermission>
      <DeletePermission>0</DeletePermission>
      <ExecutePermission>1</ExecutePermission>
      <SecurityFilter />
    </Permission>
    <Permission>
      <ObjectID>80110</ObjectID>
      <ObjectType>8</ObjectType>
      <ReadPermission>0</ReadPermission>
      <InsertPermission>0</InsertPermission>
      <ModifyPermission>0</ModifyPermission>
      <DeletePermission>0</DeletePermission>
      <ExecutePermission>1</ExecutePermission>
      <SecurityFilter />
    </Permission>
    <Permission>
      <ObjectID>80109</ObjectID>
      <ObjectType>8</ObjectType>
      <ReadPermission>0</ReadPermission>
      <InsertPermission>0</InsertPermission>
      <ModifyPermission>0</ModifyPermission>
      <DeletePermission>0</DeletePermission>
      <ExecutePermission>1</ExecutePermission>
      <SecurityFilter />
    </Permission>
    <Permission>
      <ObjectID>80101</ObjectID>
      <ObjectType>3</ObjectType>
      <ReadPermission>0</ReadPermission>
      <InsertPermission>0</InsertPermission>
      <ModifyPermission>0</ModifyPermission>
      <DeletePermission>0</DeletePermission>
      <ExecutePermission>1</ExecutePermission>
      <SecurityFilter />
    </Permission>
    <Permission>
      <ObjectID>80100</ObjectID>
      <ObjectType>3</ObjectType>
      <ReadPermission>0</ReadPermission>
      <InsertPermission>0</InsertPermission>
      <ModifyPermission>0</ModifyPermission>
      <DeletePermission>0</DeletePermission>
      <ExecutePermission>1</ExecutePermission>
      <SecurityFilter />
    </Permission>
    <Permission>
      <ObjectID>80100</ObjectID>
      <ObjectType>9</ObjectType>
      <ReadPermission>0</ReadPermission>
      <InsertPermission>0</InsertPermission>
      <ModifyPermission>0</ModifyPermission>
      <DeletePermission>0</DeletePermission>
      <ExecutePermission>1</ExecutePermission>
      <SecurityFilter />
    </Permission>
  </PermissionSet>
</PermissionSets>